vis3dpy/__init__.py
vis3dpy/plot.py
vis3dpy-0.0.2.dist-info/LICENSE
vis3dpy-0.0.2.dist-info/METADATA
vis3dpy-0.0.2.dist-info/WHEEL
vis3dpy-0.0.2.dist-info/top_level.txt
vis3dpy-0.0.2.dist-info/RECORD
