Metadata-Version: 2.1
Name: vis3dpy
Version: 0.0.2
Summary: Minimal 3D data visualizer
Home-page: https://github.com/LukasDrsman/vis3dpy
Author: Lukáš Dršman
Author-email: lukaskodr@gmail.com
License: UNKNOWN
Platform: UNKNOWN
Classifier: Programming Language :: Python :: 3
Classifier: Operating System :: OS Independent
Requires-Python: >=3.6
Requires-Dist: PyOpenGL
Requires-Dist: PyOpenGL-accelerate
Requires-Dist: pygame
